panoramax_cli/__init__.py
panoramax_cli/__main__.py
panoramax_cli/auth.py
panoramax_cli/download.py
panoramax_cli/exception.py
panoramax_cli/http.py
panoramax_cli/main.py
panoramax_cli/model.py
panoramax_cli/status.py
panoramax_cli/transfer.py
panoramax_cli/upload.py
panoramax_cli/utils.py
panoramax_cli/metadata/__init__.py
panoramax_cli/metadata/csv.py
panoramax_cli/metadata/utils.py
panoramax_cli-1.2.3.dist-info/entry_points.txt
panoramax_cli-1.2.3.dist-info/licenses/LICENSE
panoramax_cli-1.2.3.dist-info/WHEEL
panoramax_cli-1.2.3.dist-info/METADATA
panoramax_cli-1.2.3.dist-info/RECORD
