Metadata-Version: 2.4
Name: panoramax_cli
Version: 1.2.3
Summary: Panoramax client cli tool
Author-email: Antoine Desbordes <antoine.desbordes@gmail.com>, Adrien PAVIE <panieravide@riseup.net>
Requires-Python: >=3.9
Classifier: License :: OSI Approved :: MIT License
License-File: LICENSE
Requires-Dist: typer ~= 0.16
Requires-Dist: rich ~= 14.1
Requires-Dist: tomli ~= 2.2.1
Requires-Dist: tomli-w ~= 1.2.0
Requires-Dist: qrcode ~= 8.1
Requires-Dist: geopic-tag-reader  == 1.8.0
Requires-Dist: packaging ~= 25.0
Requires-Dist: httpx ~= 0.28.1
Requires-Dist: tenacity>=9.1
Requires-Dist: flit ~= 3.10.0 ; extra == "build"
Requires-Dist: pyinstaller ~= 6.12.0 ; extra == "build-binary"
Requires-Dist: ruff ~= 0.12.10 ; extra == "dev"
Requires-Dist: mypy ~= 1.17.1 ; extra == "dev"
Requires-Dist: pytest ~= 8.3 ; extra == "dev"
Requires-Dist: testcontainers ~= 4.10 ; extra == "dev"
Requires-Dist: pytest-datafiles ~= 3.0.0 ; extra == "dev"
Requires-Dist: pre-commit ~= 4.2 ; extra == "dev"
Requires-Dist: respx ~= 0.22.0 ; extra == "dev"
Requires-Dist: mkdocs-material ~= 9.6.7 ; extra == "docs"
Project-URL: Home, https://gitlab.com/panoramax/clients/cli
Provides-Extra: build
Provides-Extra: build-binary
Provides-Extra: dev
Provides-Extra: docs
